pysubdisc/VERSION
pysubdisc/__init__.py
pysubdisc/core.py
pysubdisc/interface.py
pysubdisc/java.py
pysubdisc/version.py
pysubdisc/jars/subdisc-gui-r1161.jar
pysubdisc-0.2.1161.dist-info/METADATA
pysubdisc-0.2.1161.dist-info/WHEEL
pysubdisc-0.2.1161.dist-info/licenses/LICENSE
pysubdisc-0.2.1161.dist-info/RECORD
