Metadata-Version: 2.4
Name: pysubdisc
Version: 0.2.1161
Summary: Python wrapper for SubDisc: Subgroup Discovery
Project-URL: Homepage, https://github.com/SubDisc/pySubDisc
Project-URL: Bug Tracker, https://github.com/SubDisc/pySubDisc/issues
Author-email: Willem Jan Palenstijn <w.j.palenstijn@liacs.leidenuniv.nl>
License-File: LICENSE
Classifier: License :: OSI Approved :: Apache Software License
Classifier: Operating System :: OS Independent
Classifier: Programming Language :: Python :: 3
Requires-Python: >=3.7
Requires-Dist: jpype1
Requires-Dist: pandas
Requires-Dist: scipy
